MoleKing.pypy38-pp73-x86-linux-gnu.so
src/CMakeLists.txt
src/MoleKingConfig.hpp.in
src/__init__.py
src/main.cpp
src/main2.cpp
src/berny/CMakeLists.txt
src/berny/Hessian.cpp
src/berny/Hessian.hpp
src/chemicalUnits/AtomicScale.cpp
src/chemicalUnits/AtomicScale.hpp
src/chemicalUnits/CMakeLists.txt
src/chemicalUnits/Field.hpp
src/chemicalUnits/Molecule.cpp
src/chemicalUnits/Molecule.hpp
src/chemicalUnits/OPLSff.cpp
src/chemicalUnits/OPLSff.hpp
src/chemicalUnits/PeriodicTable.cpp
src/chemicalUnits/PeriodicTable.hpp
src/chemicalUnits/SupraMolecule.cpp
src/chemicalUnits/SupraMolecule.hpp
src/chemicalUnits/pov.cpp
src/chemicalUnits/pov.hpp
src/myMath/CMakeLists.txt
src/myMath/Geometry.cpp
src/myMath/Geometry.hpp
src/myMath/MassCenter.cpp
src/myMath/MassCenter.hpp
src/myMath/Matrix.cpp
src/myMath/Matrix.hpp
src/myMath/Vectors.cpp
src/myMath/Vectors.hpp
src/outputProcess/CMakeLists.txt
src/outputProcess/G16Process.cpp
src/outputProcess/G16Process.hpp
src/outputProcess/Psi4Process.cpp
src/outputProcess/Psi4Process.hpp
moleking-1.5.4.dist-info/LICENSE.txt
moleking-1.5.4.dist-info/METADATA
moleking-1.5.4.dist-info/WHEEL
moleking-1.5.4.dist-info/top_level.txt
moleking-1.5.4.dist-info/RECORD
